gradio_audio_region/__init__.py
gradio_audio_region/audio_region.py
gradio_audio_region-0.1.0.dist-info/licenses/LICENSE
gradio_audio_region-0.1.0.dist-info/METADATA
gradio_audio_region-0.1.0.dist-info/WHEEL
gradio_audio_region-0.1.0.dist-info/top_level.txt
gradio_audio_region-0.1.0.dist-info/RECORD
