Metadata-Version: 2.4
Name: gradio-audio-region
Version: 0.1.0
Summary: Custom Gradio audio component that returns region selection timing data along with audio data
Author-email: Audio Dataset Corrector <jsaluja@example.com>
License: MIT
Project-URL: Homepage, https://github.com/jsaluja/gradio-audio-region
Project-URL: Repository, https://github.com/jsaluja/gradio-audio-region
Project-URL: Issues, https://github.com/jsaluja/gradio-audio-region/issues
Keywords: gradio,audio,editing,regions,timing
Classifier: Development Status :: 3 - Alpha
Classifier: Intended Audience :: Developers
Classifier: License :: OSI Approved :: MIT License
Classifier: Programming Language :: Python :: 3
Classifier: Programming Language :: Python :: 3.8
Classifier: Programming Language :: Python :: 3.9
Classifier: Programming Language :: Python :: 3.10
Classifier: Programming Language :: Python :: 3.11
Classifier: Topic :: Multimedia :: Sound/Audio :: Editors
Classifier: Topic :: Scientific/Engineering :: Artificial Intelligence
Requires-Python: >=3.8
License-File: LICENSE
Requires-Dist: gradio<5.0.0,>=4.0.0
Requires-Dist: numpy>=1.21.0
Provides-Extra: dev
Requires-Dist: pytest>=7.0.0; extra == "dev"
Requires-Dist: pytest-cov>=4.0.0; extra == "dev"
Requires-Dist: black>=22.0.0; extra == "dev"
Requires-Dist: isort>=5.0.0; extra == "dev"
Requires-Dist: flake8>=5.0.0; extra == "dev"
Dynamic: license-file
